plot_ellipse/__init__.py
plot_ellipse/plot.py
tests/__init__.py
tests/test_imports.py
plot_ellipse-1.0.1.dist-info/LICENSE
plot_ellipse-1.0.1.dist-info/METADATA
plot_ellipse-1.0.1.dist-info/WHEEL
plot_ellipse-1.0.1.dist-info/top_level.txt
plot_ellipse-1.0.1.dist-info/RECORD
